pattern_tiler/__init__.py
pattern_tiler/__main__.py
pattern_tiler/tile.py
pattern_tiler-0.1.0.dist-info/METADATA
pattern_tiler-0.1.0.dist-info/WHEEL
pattern_tiler-0.1.0.dist-info/entry_points.txt
pattern_tiler-0.1.0.dist-info/RECORD
