Metadata-Version: 2.1
Name: pattern-tiler
Version: 0.1.0
Summary: 
Author: Diego Canez
Author-email: canezdiego@gmail.com
Requires-Python: >=3.9,<4.0
Classifier: Programming Language :: Python :: 3
Classifier: Programming Language :: Python :: 3.9
Classifier: Programming Language :: Python :: 3.10
Classifier: Programming Language :: Python :: 3.11
Requires-Dist: pillow (>=10.0.0,<11.0.0)
